{"nodes": [{"data": {"id": "ECK120001594", "name": "1 yafD", "count": 1}}, {"data": {"id": "ECK120029169 operon", "name": "1 yafDE operon", "count": 1}}, {"data": {"id": "ECK120000166", "name": "21 cyaA", "count": 21}}, {"data": {"id": "ECK120014835 operon", "name": "21 cyaA operon", "count": 21}}, {"data": {"id": "CRP regulon", "name": "74 CRP regulon", "count": 74}}, {"data": {"id": "ECK120000391", "name": "30 glpK", "count": 30}}, {"data": {"id": "ECK120014723 operon", "name": "32 glpFKX operon", "count": 32}}, {"data": {"id": "GlpR regulon", "name": "32 GlpR regulon", "count": 32}}, {"data": {"id": "ECK120000583", "name": "2 metL", "count": 2}}, {"data": {"id": "ECK120015057 operon", "name": "2 metBL operon", "count": 2}}, {"data": {"id": "HypT regulon", "name": "2 HypT regulon", "count": 2}}, {"data": {"id": "MetJ regulon", "name": "2 MetJ regulon", "count": 2}}, {"data": {"id": "PhoP regulon", "name": "2 PhoP regulon", "count": 2}}, {"data": {"id": "ECK120000885", "name": "5 rpoB", "count": 5}}, {"data": {"id": "ECK120016992 operon", "name": "9 rplKAJL-rpoBC operon", "count": 9}}, {"data": {"id": "ECK120010201", "name": "4 hnsp", "count": 4}}, {"data": {"id": "ECK120014937 operon", "name": "6 hns operon", "count": 6}}, {"data": {"id": "H-NS regulon", "name": "10 H-NS regulon", "count": 10}}, {"data": {"id": "CspA regulon", "name": "6 CspA regulon", "count": 6}}, {"data": {"id": "Fis regulon", "name": "11 Fis regulon", "count": 11}}, {"data": {"id": "GadX regulon", "name": "6 GadX regulon", "count": 6}}, {"data": {"id": "ECK120001044/ECK120003456", "name": "1 uidA/uidR", "count": 1}}, {"data": {"id": "ECK120026438 operon", "name": "1 uidABC operon", "count": 1}}, {"data": {"id": "UidR regulon", "name": "1 UidR regulon", "count": 1}}, {"data": {"id": "UxuR regulon", "name": "1 UxuR regulon", "count": 1}}, {"data": {"id": "ECK120000161", "name": "10 crr", "count": 10}}, {"data": {"id": "ECK120014520 operon", "name": "11 ptsHI-crr operon", "count": 11}}, {"data": {"id": "NagC regulon", "name": "11 NagC regulon", "count": 11}}, {"data": {"id": "Cra regulon", "name": "13 Cra regulon", "count": 13}}, {"data": {"id": "Mlc regulon", "name": "11 Mlc regulon", "count": 11}}, {"data": {"id": "ECK120000838", "name": "2 rhsB", "count": 2}}, {"data": {"id": "ECK120028344 operon", "name": "2 rhsB operon", "count": 2}}, {"data": {"id": "ECK120002998", "name": "1 ybhD", "count": 1}}, {"data": {"id": "ECK120020927 operon", "name": "1 ybhD operon", "count": 1}}, {"data": {"id": "ECK120001543", "name": "1 moaA", "count": 1}}, {"data": {"id": "ECK120014368 operon", "name": "1 moaABCDE operon", "count": 1}}, {"data": {"id": "ModE regulon", "name": "2 ModE regulon", "count": 2}}, {"data": {"id": "CueR regulon", "name": "1 CueR regulon", "count": 1}}, {"data": {"id": "FNR regulon", "name": "4 FNR regulon", "count": 4}}, {"data": {"id": "ECK120003438", "name": "1 dmsD", "count": 1}}, {"data": {"id": "ECK120015125 operon", "name": "1 ynfEFGH-dmsD operon", "count": 1}}, {"data": {"id": "NarL regulon", "name": "2 NarL regulon", "count": 2}}, {"data": {"id": "ECK120003439", "name": "1 clcB", "count": 1}}, {"data": {"id": "ECK120028933 operon", "name": "1 clcB operon", "count": 1}}, {"data": {"id": "ECK125137156", "name": "1 flhCp3", "count": 1}}, {"data": {"id": "ECK120000314", "name": "1 flhD", "count": 1}}, {"data": {"id": "ECK120014934 operon", "name": "1 flhDC operon", "count": 1}}, {"data": {"id": "MatA regulon", "name": "1 MatA regulon", "count": 1}}, {"data": {"id": "AcrR regulon", "name": "1 AcrR regulon", "count": 1}}, {"data": {"id": "RcsAB regulon", "name": "1 RcsAB regulon", "count": 1}}, {"data": {"id": "OmpR regulon", "name": "1 OmpR regulon", "count": 1}}, {"data": {"id": "Fur regulon", "name": "3 Fur regulon", "count": 3}}, {"data": {"id": "LrhA regulon", "name": "1 LrhA regulon", "count": 1}}, {"data": {"id": "FliZ regulon", "name": "1 FliZ regulon", "count": 1}}, {"data": {"id": "HdfR regulon", "name": "1 HdfR regulon", "count": 1}}, {"data": {"id": "QseB regulon", "name": "1 QseB regulon", "count": 1}}, {"data": {"id": "IHF regulon", "name": "2 IHF regulon", "count": 2}}, {"data": {"id": "YjjQ regulon", "name": "1 YjjQ regulon", "count": 1}}, {"data": {"id": "ECK120003634", "name": "1 yedP", "count": 1}}, {"data": {"id": "ECK120023755 operon", "name": "1 yedP operon", "count": 1}}, {"data": {"id": "ECK120000133", "name": "1 cdd", "count": 1}}, {"data": {"id": "ECK120014505 operon", "name": "1 cdd operon", "count": 1}}, {"data": {"id": "CytR regulon", "name": "1 CytR regulon", "count": 1}}, {"data": {"id": "NsrR regulon", "name": "1 NsrR regulon", "count": 1}}, {"data": {"id": "ECK125137284", "name": "1 rplYp3", "count": 1}}, {"data": {"id": "ECK120001961", "name": "1 radD", "count": 1}}, {"data": {"id": "ECK125203372 operon", "name": "1 radD operon", "count": 1}}, {"data": {"id": "ECK120001976", "name": "1 napA", "count": 1}}, {"data": {"id": "ECK120014586 operon", "name": "1 napFDAGHBC-ccmABCDEFGH operon", "count": 1}}, {"data": {"id": "NarP regulon", "name": "1 NarP regulon", "count": 1}}, {"data": {"id": "FlhDC regulon", "name": "1 FlhDC regulon", "count": 1}}, {"data": {"id": "IscR regulon", "name": "1 IscR regulon", "count": 1}}, {"data": {"id": "ECK120002230", "name": "1 menF", "count": 1}}, {"data": {"id": "ECK120034519 operon", "name": "1 menFDHBCE operon", "count": 1}}, {"data": {"id": "ECK120003870", "name": "1 tmcA", "count": 1}}, {"data": {"id": "ECK120035060 operon", "name": "1 ypfJ-tmcA operon", "count": 1}}, {"data": {"id": "ECK120000101", "name": "1 atpH", "count": 1}}, {"data": {"id": "ECK120014782 operon", "name": "1 atpIBEFHAGDC operon", "count": 1}}, {"data": {"id": "ECK120001784", "name": "1 yiiD", "count": 1}}, {"data": {"id": "ECK120028237 operon", "name": "1 yihXY-dtd-yiiD operon", "count": 1}}, {"data": {"id": "ECK120001745", "name": "1 aidB", "count": 1}}, {"data": {"id": "ECK120014903 operon", "name": "1 aidB operon", "count": 1}}, {"data": {"id": "Ada regulon", "name": "1 Ada regulon", "count": 1}}, {"data": {"id": "Lrp regulon", "name": "2 Lrp regulon", "count": 2}}, {"data": {"id": "AidB regulon", "name": "1 AidB regulon", "count": 1}}, {"data": {"id": "ECK120016925", "name": "1 yjhW", "count": 1}}, {"data": {"id": "ECK120028130 operon", "name": "1 insO-2-yjhWV operon", "count": 1}}, {"data": {"id": "ECK120011932", "name": "1 hns TFBS", "count": 1}}, {"data": {"id": "ECK120001548/ECK120002618", "name": "2 mstA/C0614", "count": 2}}, {"data": {"id": "ECK120002346/ECK120002347", "name": "1 mdaB/ygiN", "count": 1}}, {"data": {"id": "ECK120002200", "name": "1 yadK", "count": 1}}, {"data": {"id": "ECK120030520 operon", "name": "1 yadMLKC operon", "count": 1}}, {"data": {"id": "ECK120002285/ECK120001647", "name": "1 tomB/acrB", "count": 1}}, {"data": {"id": "ECK120035065 operon", "name": "1 tomB-hha operon", "count": 1}}, {"data": {"id": "BasR regulon", "name": "1 BasR regulon", "count": 1}}, {"data": {"id": "CpxR regulon", "name": "1 CpxR regulon", "count": 1}}, {"data": {"id": "PdhR regulon", "name": "1 PdhR regulon", "count": 1}}, {"data": {"id": "ECK120010797", "name": "1 ptsHI-crr terminator", "count": 1}}, {"data": {"id": "ECK120003833", "name": "1 pdxK", "count": 1}}, {"data": {"id": "ECK120020944 operon", "name": "1 pdxK operon", "count": 1}}, {"data": {"id": "ECK120013464", "name": "2 glpFKX TFBS", "count": 2}}, {"data": {"id": "ECK125143560", "name": "3 leuLABCD attenuator terminator", "count": 3}}, {"data": {"id": "ECK120014726 operon", "name": "3 leuLABCD operon", "count": 3}}, {"data": {"id": "LeuO regulon", "name": "4 LeuO regulon", "count": 4}}, {"data": {"id": "ECK120000160", "name": "1 crp", "count": 1}}, {"data": {"id": "ECK120014920 operon", "name": "1 crp operon", "count": 1}}, {"data": {"id": "ECK125257016", "name": "1 carAB terminator", "count": 1}}, {"data": {"id": "ECK120014911 operon", "name": "1 carAB operon", "count": 1}}, {"data": {"id": "ArgR regulon", "name": "3 ArgR regulon", "count": 3}}, {"data": {"id": "PepA regulon", "name": "1 PepA regulon", "count": 1}}, {"data": {"id": "RutR regulon", "name": "1 RutR regulon", "count": 1}}, {"data": {"id": "PurR regulon", "name": "1 PurR regulon", "count": 1}}, {"data": {"id": "ECK120003992/ECK120003993", "name": "1 casD/casC", "count": 1}}, {"data": {"id": "ECK125095154 operon", "name": "1 casABCDE12 operon", "count": 1}}, {"data": {"id": "SlyA regulon", "name": "2 SlyA regulon", "count": 2}}, {"data": {"id": "ECK120003274/ECK120003275", "name": "1 ydaG/racR", "count": 1}}, {"data": {"id": "ECK125144241", "name": "6 hisLGDCBHAFI attenuator terminator", "count": 6}}, {"data": {"id": "ECK120016918 operon", "name": "6 hisLGDCBHAFI operon", "count": 6}}, {"data": {"id": "ECK120002031/ECK120001303", "name": "1 uraA/upp", "count": 1}}, {"data": {"id": "ECK120014693 operon", "name": "1 upp-uraA operon", "count": 1}}, {"data": {"id": "ECK125144631", "name": "2 metY-rimP-nusA-infB-rbfA-truB-rpsO-pnp attenuator terminator", "count": 2}}, {"data": {"id": "ECK125095173 operon", "name": "2 metY-rimP-nusA-infB-rbfA-truB-rpsO-pnp operon", "count": 2}}, {"data": {"id": "ECK120004404/ECK120002319", "name": "1 yjhU/yjhF", "count": 1}}, {"data": {"id": "ECK120011926", "name": "1 hns TFBS", "count": 1}}, {"data": {"id": "ECK120000903", "name": "1 rpsM", "count": 1}}, {"data": {"id": "ECK120014638 operon", "name": "3 rpsMKD-rpoA-rplQ operon", "count": 3}}, {"data": {"id": "ECK120000886", "name": "4 rpoC", "count": 4}}, {"data": {"id": "ECK120001349/ECK120004144", "name": "1 glgS/yqiJ", "count": 1}}, {"data": {"id": "ECK120014684 operon", "name": "1 glgS operon", "count": 1}}, {"data": {"id": "ECK120001091", "name": "2 fimZ", "count": 2}}, {"data": {"id": "ECK120023665 operon", "name": "2 fimZ operon", "count": 2}}, {"data": {"id": "ECK120002835", "name": "1 yaiT", "count": 1}}, {"data": {"id": "ECK120020912 operon", "name": "1 yaiT operon", "count": 1}}, {"data": {"id": "ECK120002403/ECK120000662", "name": "1 matP/ompA", "count": 1}}, {"data": {"id": "ECK120000276", "name": "1 fbaA", "count": 1}}, {"data": {"id": "ECK120015844 operon", "name": "1 epd-pgk-fbaA operon", "count": 1}}, {"data": {"id": "ECK120001833", "name": "1 gldA", "count": 1}}, {"data": {"id": "ECK120028251 operon", "name": "1 ptsA-fsaB-gldA operon", "count": 1}}, {"data": {"id": "ECK120033723", "name": "1 yfdXp", "count": 1}}, {"data": {"id": "ECK125162051 operon", "name": "1 yfdX-frc-oxc-yfdVE operon", "count": 1}}, {"data": {"id": "EvgA regulon", "name": "1 EvgA regulon", "count": 1}}, {"data": {"id": "ECK120001029/ECK120030090", "name": "1 tyrB/yjbS", "count": 1}}, {"data": {"id": "ECK120014896 operon", "name": "1 tyrB operon", "count": 1}}, {"data": {"id": "TyrR regulon", "name": "1 TyrR regulon", "count": 1}}, {"data": {"id": "ECK120000598/ECK120000296", "name": "1 mrcB/fhuA", "count": 1}}, {"data": {"id": "ECK120014837 operon", "name": "1 fhuACDB operon", "count": 1}}, {"data": {"id": "ECK120002891/ECK120002892", "name": "2 glxK/allE", "count": 2}}, {"data": {"id": "ECK120010783", "name": "2 opgGH terminator", "count": 2}}, {"data": {"id": "ECK125143900", "name": "2 yceK attenuator terminator", "count": 2}}, {"data": {"id": "ECK125165360 operon", "name": "2 opgGH operon", "count": 2}}, {"data": {"id": "ECK120028979 operon", "name": "2 yceK operon", "count": 2}}, {"data": {"id": "ECK120003553/ECK120003554", "name": "1 yeaD/yeaE", "count": 1}}, {"data": {"id": "ECK120033617", "name": "2 yhdNp", "count": 2}}, {"data": {"id": "ECK120010871", "name": "2 rpsMKD-rpoA-rplQ terminator", "count": 2}}, {"data": {"id": "ECK120028314 operon", "name": "2 yhdN-zntR operon", "count": 2}}, {"data": {"id": "ECK120002341", "name": "1 gntK", "count": 1}}, {"data": {"id": "ECK120014768 operon", "name": "1 gntRKU operon", "count": 1}}, {"data": {"id": "GntR regulon", "name": "1 GntR regulon", "count": 1}}, {"data": {"id": "IdnR regulon", "name": "1 IdnR regulon", "count": 1}}, {"data": {"id": "ECK120002520", "name": "1 rrlB", "count": 1}}, {"data": {"id": "ECK120023947 operon", "name": "1 rrsB-gltT-rrlB-rrfB operon", "count": 1}}, {"data": {"id": "ECK125136882", "name": "1 insHp7", "count": 1}}, {"data": {"id": "ECK125136879", "name": "1 mppAp5", "count": 1}}, {"data": {"id": "ECK125136881", "name": "1 mppAp13", "count": 1}}, {"data": {"id": "ECK125136880", "name": "1 mppAp9", "count": 1}}, {"data": {"id": "ECK120034219", "name": "1 ynaIp", "count": 1}}, {"data": {"id": "ECK125136878", "name": "1 mppAp4", "count": 1}}, {"data": {"id": "ECK125143994", "name": "1 ynaI attenuator terminator", "count": 1}}, {"data": {"id": "ECK125143996", "name": "1 insH-4 attenuator terminator", "count": 1}}, {"data": {"id": "ECK120003260", "name": "1 mppA", "count": 1}}, {"data": {"id": "ECK120003259", "name": "1 pgrR", "count": 1}}, {"data": {"id": "ECK120003261", "name": "1 ynaI", "count": 1}}, {"data": {"id": "ECK120023839 operon", "name": "3 ynaI operon", "count": 3}}, {"data": {"id": "ECK120028832 operon", "name": "1 insH-4 operon", "count": 1}}, {"data": {"id": "ECK120028944 operon", "name": "1 mppA operon", "count": 1}}, {"data": {"id": "ECK125160635 operon", "name": "1 pgrR operon", "count": 1}}, {"data": {"id": "ECK120004249", "name": "1 gspE", "count": 1}}, {"data": {"id": "ECK120028315 operon", "name": "1 gspCDEFGHIJKLMO operon", "count": 1}}, {"data": {"id": "ECK125136750", "name": "1 yceQp6", "count": 1}}, {"data": {"id": "ECK120002259", "name": "1 dgcE", "count": 1}}, {"data": {"id": "ECK125229280 operon", "name": "1 dgcE operon", "count": 1}}], "edges": [{"data": {"id": "ECK120029169 operon-ECK120001594", "target": "ECK120029169 operon", "source": "ECK120001594", "count": 1}}, {"data": {"id": "ECK120014835 operon-ECK120000166", "target": "ECK120014835 operon", "source": "ECK120000166", "count": 21}}, {"data": {"id": "CRP regulon-ECK120014835 operon", "target": "CRP regulon", "source": "ECK120014835 operon", "count": 21}}, {"data": {"id": "ECK120014723 operon-ECK120000391", "target": "ECK120014723 operon", "source": "ECK120000391", "count": 30}}, {"data": {"id": "GlpR regulon-ECK120014723 operon", "target": "GlpR regulon", "source": "ECK120014723 operon", "count": 32}}, {"data": {"id": "CRP regulon-ECK120014723 operon", "target": "CRP regulon", "source": "ECK120014723 operon", "count": 32}}, {"data": {"id": "ECK120015057 operon-ECK120000583", "target": "ECK120015057 operon", "source": "ECK120000583", "count": 2}}, {"data": {"id": "HypT regulon-ECK120015057 operon", "target": "HypT regulon", "source": "ECK120015057 operon", "count": 2}}, {"data": {"id": "MetJ regulon-ECK120015057 operon", "target": "MetJ regulon", "source": "ECK120015057 operon", "count": 2}}, {"data": {"id": "PhoP regulon-ECK120015057 operon", "target": "PhoP regulon", "source": "ECK120015057 operon", "count": 2}}, {"data": {"id": "ECK120016992 operon-ECK120000885", "target": "ECK120016992 operon", "source": "ECK120000885", "count": 5}}, {"data": {"id": "ECK120014937 operon-ECK120010201", "target": "ECK120014937 operon", "source": "ECK120010201", "count": 4}}, {"data": {"id": "CspA regulon-ECK120014937 operon", "target": "CspA regulon", "source": "ECK120014937 operon", "count": 6}}, {"data": {"id": "Fis regulon-ECK120014937 operon", "target": "Fis regulon", "source": "ECK120014937 operon", "count": 6}}, {"data": {"id": "GadX regulon-ECK120014937 operon", "target": "GadX regulon", "source": "ECK120014937 operon", "count": 6}}, {"data": {"id": "H-NS regulon-ECK120014937 operon", "target": "H-NS regulon", "source": "ECK120014937 operon", "count": 6}}, {"data": {"id": "ECK120026438 operon-ECK120001044/ECK120003456", "target": "ECK120026438 operon", "source": "ECK120001044/ECK120003456", "count": 1}}, {"data": {"id": "UidR regulon-ECK120026438 operon", "target": "UidR regulon", "source": "ECK120026438 operon", "count": 1}}, {"data": {"id": "CRP regulon-ECK120026438 operon", "target": "CRP regulon", "source": "ECK120026438 operon", "count": 1}}, {"data": {"id": "UxuR regulon-ECK120026438 operon", "target": "UxuR regulon", "source": "ECK120026438 operon", "count": 1}}, {"data": {"id": "ECK120014520 operon-ECK120000161", "target": "ECK120014520 operon", "source": "ECK120000161", "count": 10}}, {"data": {"id": "CRP regulon-ECK120014520 operon", "target": "CRP regulon", "source": "ECK120014520 operon", "count": 11}}, {"data": {"id": "NagC regulon-ECK120014520 operon", "target": "NagC regulon", "source": "ECK120014520 operon", "count": 11}}, {"data": {"id": "Cra regulon-ECK120014520 operon", "target": "Cra regulon", "source": "ECK120014520 operon", "count": 11}}, {"data": {"id": "Mlc regulon-ECK120014520 operon", "target": "Mlc regulon", "source": "ECK120014520 operon", "count": 11}}, {"data": {"id": "ECK120028344 operon-ECK120000838", "target": "ECK120028344 operon", "source": "ECK120000838", "count": 2}}, {"data": {"id": "ECK120020927 operon-ECK120002998", "target": "ECK120020927 operon", "source": "ECK120002998", "count": 1}}, {"data": {"id": "ECK120014368 operon-ECK120001543", "target": "ECK120014368 operon", "source": "ECK120001543", "count": 1}}, {"data": {"id": "CueR regulon-ECK120014368 operon", "target": "CueR regulon", "source": "ECK120014368 operon", "count": 1}}, {"data": {"id": "FNR regulon-ECK120014368 operon", "target": "FNR regulon", "source": "ECK120014368 operon", "count": 1}}, {"data": {"id": "ModE regulon-ECK120014368 operon", "target": "ModE regulon", "source": "ECK120014368 operon", "count": 1}}, {"data": {"id": "ECK120015125 operon-ECK120003438", "target": "ECK120015125 operon", "source": "ECK120003438", "count": 1}}, {"data": {"id": "NarL regulon-ECK120015125 operon", "target": "NarL regulon", "source": "ECK120015125 operon", "count": 1}}, {"data": {"id": "FNR regulon-ECK120015125 operon", "target": "FNR regulon", "source": "ECK120015125 operon", "count": 1}}, {"data": {"id": "ECK120028933 operon-ECK120003439", "target": "ECK120028933 operon", "source": "ECK120003439", "count": 1}}, {"data": {"id": "ECK120014934 operon-ECK125137156", "target": "ECK120014934 operon", "source": "ECK125137156", "count": 1}}, {"data": {"id": "ECK120014934 operon-ECK120000314", "target": "ECK120014934 operon", "source": "ECK120000314", "count": 1}}, {"data": {"id": "AcrR regulon-ECK120014934 operon", "target": "AcrR regulon", "source": "ECK120014934 operon", "count": 1}}, {"data": {"id": "RcsAB regulon-ECK120014934 operon", "target": "RcsAB regulon", "source": "ECK120014934 operon", "count": 1}}, {"data": {"id": "MatA regulon-ECK120014934 operon", "target": "MatA regulon", "source": "ECK120014934 operon", "count": 1}}, {"data": {"id": "H-NS regulon-ECK120014934 operon", "target": "H-NS regulon", "source": "ECK120014934 operon", "count": 1}}, {"data": {"id": "OmpR regulon-ECK120014934 operon", "target": "OmpR regulon", "source": "ECK120014934 operon", "count": 1}}, {"data": {"id": "Fur regulon-ECK120014934 operon", "target": "Fur regulon", "source": "ECK120014934 operon", "count": 1}}, {"data": {"id": "LrhA regulon-ECK120014934 operon", "target": "LrhA regulon", "source": "ECK120014934 operon", "count": 1}}, {"data": {"id": "FliZ regulon-ECK120014934 operon", "target": "FliZ regulon", "source": "ECK120014934 operon", "count": 1}}, {"data": {"id": "HdfR regulon-ECK120014934 operon", "target": "HdfR regulon", "source": "ECK120014934 operon", "count": 1}}, {"data": {"id": "CRP regulon-ECK120014934 operon", "target": "CRP regulon", "source": "ECK120014934 operon", "count": 1}}, {"data": {"id": "QseB regulon-ECK120014934 operon", "target": "QseB regulon", "source": "ECK120014934 operon", "count": 1}}, {"data": {"id": "YjjQ regulon-ECK120014934 operon", "target": "YjjQ regulon", "source": "ECK120014934 operon", "count": 1}}, {"data": {"id": "IHF regulon-ECK120014934 operon", "target": "IHF regulon", "source": "ECK120014934 operon", "count": 1}}, {"data": {"id": "ECK120023755 operon-ECK120003634", "target": "ECK120023755 operon", "source": "ECK120003634", "count": 1}}, {"data": {"id": "ECK120014505 operon-ECK120000133", "target": "ECK120014505 operon", "source": "ECK120000133", "count": 1}}, {"data": {"id": "CytR regulon-ECK120014505 operon", "target": "CytR regulon", "source": "ECK120014505 operon", "count": 1}}, {"data": {"id": "CRP regulon-ECK120014505 operon", "target": "CRP regulon", "source": "ECK120014505 operon", "count": 1}}, {"data": {"id": "NsrR regulon-ECK120014505 operon", "target": "NsrR regulon", "source": "ECK120014505 operon", "count": 1}}, {"data": {"id": "ECK125203372 operon-ECK120001961", "target": "ECK125203372 operon", "source": "ECK120001961", "count": 1}}, {"data": {"id": "ECK125203372 operon-ECK125137284", "target": "ECK125203372 operon", "source": "ECK125137284", "count": 1}}, {"data": {"id": "ECK120014586 operon-ECK120001976", "target": "ECK120014586 operon", "source": "ECK120001976", "count": 1}}, {"data": {"id": "NarP regulon-ECK120014586 operon", "target": "NarP regulon", "source": "ECK120014586 operon", "count": 1}}, {"data": {"id": "ModE regulon-ECK120014586 operon", "target": "ModE regulon", "source": "ECK120014586 operon", "count": 1}}, {"data": {"id": "FNR regulon-ECK120014586 operon", "target": "FNR regulon", "source": "ECK120014586 operon", "count": 1}}, {"data": {"id": "IscR regulon-ECK120014586 operon", "target": "IscR regulon", "source": "ECK120014586 operon", "count": 1}}, {"data": {"id": "FlhDC regulon-ECK120014586 operon", "target": "FlhDC regulon", "source": "ECK120014586 operon", "count": 1}}, {"data": {"id": "NarL regulon-ECK120014586 operon", "target": "NarL regulon", "source": "ECK120014586 operon", "count": 1}}, {"data": {"id": "ECK120034519 operon-ECK120002230", "target": "ECK120034519 operon", "source": "ECK120002230", "count": 1}}, {"data": {"id": "ECK120035060 operon-ECK120003870", "target": "ECK120035060 operon", "source": "ECK120003870", "count": 1}}, {"data": {"id": "ECK120014782 operon-ECK120000101", "target": "ECK120014782 operon", "source": "ECK120000101", "count": 1}}, {"data": {"id": "ECK120028237 operon-ECK120001784", "target": "ECK120028237 operon", "source": "ECK120001784", "count": 1}}, {"data": {"id": "ECK120014903 operon-ECK120001745", "target": "ECK120014903 operon", "source": "ECK120001745", "count": 1}}, {"data": {"id": "Ada regulon-ECK120014903 operon", "target": "Ada regulon", "source": "ECK120014903 operon", "count": 1}}, {"data": {"id": "Lrp regulon-ECK120014903 operon", "target": "Lrp regulon", "source": "ECK120014903 operon", "count": 1}}, {"data": {"id": "AidB regulon-ECK120014903 operon", "target": "AidB regulon", "source": "ECK120014903 operon", "count": 1}}, {"data": {"id": "ECK120028130 operon-ECK120016925", "target": "ECK120028130 operon", "source": "ECK120016925", "count": 1}}, {"data": {"id": "ECK120014937 operon-ECK120011932", "target": "ECK120014937 operon", "source": "ECK120011932", "count": 1}}, {"data": {"id": "ECK120030520 operon-ECK120002200", "target": "ECK120030520 operon", "source": "ECK120002200", "count": 1}}, {"data": {"id": "ECK120035065 operon-ECK120002285/ECK120001647", "target": "ECK120035065 operon", "source": "ECK120002285/ECK120001647", "count": 1}}, {"data": {"id": "PdhR regulon-ECK120035065 operon", "target": "PdhR regulon", "source": "ECK120035065 operon", "count": 1}}, {"data": {"id": "CpxR regulon-ECK120035065 operon", "target": "CpxR regulon", "source": "ECK120035065 operon", "count": 1}}, {"data": {"id": "BasR regulon-ECK120035065 operon", "target": "BasR regulon", "source": "ECK120035065 operon", "count": 1}}, {"data": {"id": "ECK120020944 operon-ECK120003833", "target": "ECK120020944 operon", "source": "ECK120003833", "count": 1}}, {"data": {"id": "ECK120014520 operon-ECK120010797", "target": "ECK120014520 operon", "source": "ECK120010797", "count": 1}}, {"data": {"id": "ECK120014723 operon-ECK120013464", "target": "ECK120014723 operon", "source": "ECK120013464", "count": 2}}, {"data": {"id": "ECK120014726 operon-ECK125143560", "target": "ECK120014726 operon", "source": "ECK125143560", "count": 3}}, {"data": {"id": "LeuO regulon-ECK120014726 operon", "target": "LeuO regulon", "source": "ECK120014726 operon", "count": 3}}, {"data": {"id": "ECK120014920 operon-ECK120000160", "target": "ECK120014920 operon", "source": "ECK120000160", "count": 1}}, {"data": {"id": "Fis regulon-ECK120014920 operon", "target": "Fis regulon", "source": "ECK120014920 operon", "count": 1}}, {"data": {"id": "Cra regulon-ECK120014920 operon", "target": "Cra regulon", "source": "ECK120014920 operon", "count": 1}}, {"data": {"id": "CRP regulon-ECK120014920 operon", "target": "CRP regulon", "source": "ECK120014920 operon", "count": 1}}, {"data": {"id": "ECK120014911 operon-ECK125257016", "target": "ECK120014911 operon", "source": "ECK125257016", "count": 1}}, {"data": {"id": "PepA regulon-ECK120014911 operon", "target": "PepA regulon", "source": "ECK120014911 operon", "count": 1}}, {"data": {"id": "RutR regulon-ECK120014911 operon", "target": "RutR regulon", "source": "ECK120014911 operon", "count": 1}}, {"data": {"id": "PurR regulon-ECK120014911 operon", "target": "PurR regulon", "source": "ECK120014911 operon", "count": 1}}, {"data": {"id": "Fis regulon-ECK120014911 operon", "target": "Fis regulon", "source": "ECK120014911 operon", "count": 1}}, {"data": {"id": "ArgR regulon-ECK120014911 operon", "target": "ArgR regulon", "source": "ECK120014911 operon", "count": 1}}, {"data": {"id": "IHF regulon-ECK120014911 operon", "target": "IHF regulon", "source": "ECK120014911 operon", "count": 1}}, {"data": {"id": "ECK125095154 operon-ECK120003992/ECK120003993", "target": "ECK125095154 operon", "source": "ECK120003992/ECK120003993", "count": 1}}, {"data": {"id": "SlyA regulon-ECK125095154 operon", "target": "SlyA regulon", "source": "ECK125095154 operon", "count": 1}}, {"data": {"id": "LeuO regulon-ECK125095154 operon", "target": "LeuO regulon", "source": "ECK125095154 operon", "count": 1}}, {"data": {"id": "CRP regulon-ECK125095154 operon", "target": "CRP regulon", "source": "ECK125095154 operon", "count": 1}}, {"data": {"id": "H-NS regulon-ECK125095154 operon", "target": "H-NS regulon", "source": "ECK125095154 operon", "count": 1}}, {"data": {"id": "ECK120016918 operon-ECK125144241", "target": "ECK120016918 operon", "source": "ECK125144241", "count": 6}}, {"data": {"id": "ECK120014693 operon-ECK120002031/ECK120001303", "target": "ECK120014693 operon", "source": "ECK120002031/ECK120001303", "count": 1}}, {"data": {"id": "FNR regulon-ECK120014693 operon", "target": "FNR regulon", "source": "ECK120014693 operon", "count": 1}}, {"data": {"id": "ECK125095173 operon-ECK125144631", "target": "ECK125095173 operon", "source": "ECK125144631", "count": 2}}, {"data": {"id": "Fis regulon-ECK125095173 operon", "target": "Fis regulon", "source": "ECK125095173 operon", "count": 2}}, {"data": {"id": "ArgR regulon-ECK125095173 operon", "target": "ArgR regulon", "source": "ECK125095173 operon", "count": 2}}, {"data": {"id": "CRP regulon-ECK125095173 operon", "target": "CRP regulon", "source": "ECK125095173 operon", "count": 2}}, {"data": {"id": "ECK120014937 operon-ECK120011926", "target": "ECK120014937 operon", "source": "ECK120011926", "count": 1}}, {"data": {"id": "ECK120014638 operon-ECK120000903", "target": "ECK120014638 operon", "source": "ECK120000903", "count": 1}}, {"data": {"id": "ECK120016992 operon-ECK120000886", "target": "ECK120016992 operon", "source": "ECK120000886", "count": 4}}, {"data": {"id": "ECK120014684 operon-ECK120001349/ECK120004144", "target": "ECK120014684 operon", "source": "ECK120001349/ECK120004144", "count": 1}}, {"data": {"id": "CRP regulon-ECK120014684 operon", "target": "CRP regulon", "source": "ECK120014684 operon", "count": 1}}, {"data": {"id": "ECK120023665 operon-ECK120001091", "target": "ECK120023665 operon", "source": "ECK120001091", "count": 2}}, {"data": {"id": "ECK120020912 operon-ECK120002835", "target": "ECK120020912 operon", "source": "ECK120002835", "count": 1}}, {"data": {"id": "ECK120015844 operon-ECK120000276", "target": "ECK120015844 operon", "source": "ECK120000276", "count": 1}}, {"data": {"id": "Cra regulon-ECK120015844 operon", "target": "Cra regulon", "source": "ECK120015844 operon", "count": 1}}, {"data": {"id": "CRP regulon-ECK120015844 operon", "target": "CRP regulon", "source": "ECK120015844 operon", "count": 1}}, {"data": {"id": "ECK120028251 operon-ECK120001833", "target": "ECK120028251 operon", "source": "ECK120001833", "count": 1}}, {"data": {"id": "ECK125162051 operon-ECK120033723", "target": "ECK125162051 operon", "source": "ECK120033723", "count": 1}}, {"data": {"id": "EvgA regulon-ECK125162051 operon", "target": "EvgA regulon", "source": "ECK125162051 operon", "count": 1}}, {"data": {"id": "ECK120014896 operon-ECK120001029/ECK120030090", "target": "ECK120014896 operon", "source": "ECK120001029/ECK120030090", "count": 1}}, {"data": {"id": "TyrR regulon-ECK120014896 operon", "target": "TyrR regulon", "source": "ECK120014896 operon", "count": 1}}, {"data": {"id": "ECK120014837 operon-ECK120000598/ECK120000296", "target": "ECK120014837 operon", "source": "ECK120000598/ECK120000296", "count": 1}}, {"data": {"id": "Fur regulon-ECK120014837 operon", "target": "Fur regulon", "source": "ECK120014837 operon", "count": 1}}, {"data": {"id": "ECK120028979 operon-ECK125143900", "target": "ECK120028979 operon", "source": "ECK125143900", "count": 2}}, {"data": {"id": "ECK120028979 operon-ECK120010783", "target": "ECK120028979 operon", "source": "ECK120010783", "count": 2}}, {"data": {"id": "ECK125165360 operon-ECK125143900", "target": "ECK125165360 operon", "source": "ECK125143900", "count": 2}}, {"data": {"id": "ECK125165360 operon-ECK120010783", "target": "ECK125165360 operon", "source": "ECK120010783", "count": 2}}, {"data": {"id": "ECK120028314 operon-ECK120033617", "target": "ECK120028314 operon", "source": "ECK120033617", "count": 2}}, {"data": {"id": "ECK120028314 operon-ECK120010871", "target": "ECK120028314 operon", "source": "ECK120010871", "count": 2}}, {"data": {"id": "ECK120014638 operon-ECK120033617", "target": "ECK120014638 operon", "source": "ECK120033617", "count": 2}}, {"data": {"id": "ECK120014638 operon-ECK120010871", "target": "ECK120014638 operon", "source": "ECK120010871", "count": 2}}, {"data": {"id": "ECK120014768 operon-ECK120002341", "target": "ECK120014768 operon", "source": "ECK120002341", "count": 1}}, {"data": {"id": "CRP regulon-ECK120014768 operon", "target": "CRP regulon", "source": "ECK120014768 operon", "count": 1}}, {"data": {"id": "GntR regulon-ECK120014768 operon", "target": "GntR regulon", "source": "ECK120014768 operon", "count": 1}}, {"data": {"id": "IdnR regulon-ECK120014768 operon", "target": "IdnR regulon", "source": "ECK120014768 operon", "count": 1}}, {"data": {"id": "ECK120023947 operon-ECK120002520", "target": "ECK120023947 operon", "source": "ECK120002520", "count": 1}}, {"data": {"id": "Fis regulon-ECK120023947 operon", "target": "Fis regulon", "source": "ECK120023947 operon", "count": 1}}, {"data": {"id": "H-NS regulon-ECK120023947 operon", "target": "H-NS regulon", "source": "ECK120023947 operon", "count": 1}}, {"data": {"id": "Lrp regulon-ECK120023947 operon", "target": "Lrp regulon", "source": "ECK120023947 operon", "count": 1}}, {"data": {"id": "ECK120023839 operon-ECK125136882", "target": "ECK120023839 operon", "source": "ECK125136882", "count": 1}}, {"data": {"id": "ECK120023839 operon-ECK120034219", "target": "ECK120023839 operon", "source": "ECK120034219", "count": 1}}, {"data": {"id": "ECK120023839 operon-ECK125143996", "target": "ECK120023839 operon", "source": "ECK125143996", "count": 1}}, {"data": {"id": "ECK120023839 operon-ECK125143994", "target": "ECK120023839 operon", "source": "ECK125143994", "count": 1}}, {"data": {"id": "ECK120023839 operon-ECK120003261", "target": "ECK120023839 operon", "source": "ECK120003261", "count": 1}}, {"data": {"id": "ECK120028944 operon-ECK120003260", "target": "ECK120028944 operon", "source": "ECK120003260", "count": 1}}, {"data": {"id": "ECK125160635 operon-ECK120003259", "target": "ECK125160635 operon", "source": "ECK120003259", "count": 1}}, {"data": {"id": "ECK120028832 operon-ECK125136882", "target": "ECK120028832 operon", "source": "ECK125136882", "count": 1}}, {"data": {"id": "ECK120028832 operon-ECK120034219", "target": "ECK120028832 operon", "source": "ECK120034219", "count": 1}}, {"data": {"id": "ECK120028832 operon-ECK125143996", "target": "ECK120028832 operon", "source": "ECK125143996", "count": 1}}, {"data": {"id": "ECK120028832 operon-ECK125143994", "target": "ECK120028832 operon", "source": "ECK125143994", "count": 1}}, {"data": {"id": "ECK120028315 operon-ECK120004249", "target": "ECK120028315 operon", "source": "ECK120004249", "count": 1}}, {"data": {"id": "SlyA regulon-ECK120028315 operon", "target": "SlyA regulon", "source": "ECK120028315 operon", "count": 1}}, {"data": {"id": "H-NS regulon-ECK120028315 operon", "target": "H-NS regulon", "source": "ECK120028315 operon", "count": 1}}, {"data": {"id": "Fur regulon-ECK120028315 operon", "target": "Fur regulon", "source": "ECK120028315 operon", "count": 1}}, {"data": {"id": "ECK125229280 operon-ECK120002259", "target": "ECK125229280 operon", "source": "ECK120002259", "count": 1}}]}